surveydata/__init__.py
surveydata/azureblobstorage.py
surveydata/dynamodbstorage.py
surveydata/filestorage.py
surveydata/googlecloudstorage.py
surveydata/odkexportstorage.py
surveydata/odkplatform.py
surveydata/s3storage.py
surveydata/storagesystem.py
surveydata/surveyctoexportstorage.py
surveydata/surveyctoplatform.py
surveydata/surveyplatform.py
surveydata-0.1.13.dist-info/LICENSE
surveydata-0.1.13.dist-info/METADATA
surveydata-0.1.13.dist-info/WHEEL
surveydata-0.1.13.dist-info/top_level.txt
surveydata-0.1.13.dist-info/RECORD
