Metadata-Version: 2.1
Name: surveydata
Version: 0.1.13
Summary: Flexible access to survey data
Home-page: https://github.com/orangechairlabs/py-surveydata
Author: Christopher Robert
Author-email: crobert@orangechairlabs.com
License: Apache 2.0
Project-URL: Documentation, https://surveydata.readthedocs.io/
Platform: UNKNOWN
Requires-Python: >=3.7
License-File: LICENSE
Requires-Dist: requests
Requires-Dist: pandas
Requires-Dist: numpy
Requires-Dist: boto3
Requires-Dist: botocore
Requires-Dist: google-cloud-storage
Requires-Dist: azure-storage-blob
Requires-Dist: azure-identity
Requires-Dist: pyodk
Requires-Dist: python-dateutil
Requires-Dist: flatten-json
